sloot/main.py
sloot-0.1.0.dist-info/WHEEL
sloot-0.1.0.dist-info/METADATA
sloot-0.1.0.dist-info/RECORD
