Metadata-Version: 2.1
Name: sloot
Version: 0.1.0
Summary: tools I usually use
License: MIT
Author: Ja-sonYun
Author-email: killa30867@gmail.com
Requires-Python: >=3.8,<4.0
Classifier: License :: OSI Approved :: MIT License
Classifier: Programming Language :: Python :: 3
Classifier: Programming Language :: Python :: 3.8
Classifier: Programming Language :: Python :: 3.9
Classifier: Programming Language :: Python :: 3.10
